py_file_type/__init__.py
py_file_type/compat.py
py_file_type/loader.py
py_file_type/magic.py
py_file_type/libmagic/libmagic.dll
py_file_type/libmagic/magic.mgc
py_file_type-0.1.0.data/data/py_file_type/libmagic.dll
py_file_type-0.1.0.data/data/py_file_type/magic.mgc
py_file_type-0.1.0.dist-info/METADATA
py_file_type-0.1.0.dist-info/WHEEL
py_file_type-0.1.0.dist-info/top_level.txt
py_file_type-0.1.0.dist-info/RECORD
