Metadata-Version: 2.1
Name: py-file-type
Version: 0.1.0
Summary: Wrapper for python-magic that includes necessary bin files.
Home-page: https://github.com/riad-azz/py-file-type
Author: riad-azz
Author-email: riadh.azzoun@hotmail.com
License: MIT License
Project-URL: Source, https://github.com/riad-azz/py-file-type
Keywords: python-magic wrapper,python-magic-bin,python-magic binaries,libmagic
Classifier: Development Status :: 5 - Production/Stable
Classifier: Intended Audience :: Developers
Classifier: Natural Language :: English
Classifier: Programming Language :: Python :: 3.11
Classifier: License :: OSI Approved :: MIT License
Classifier: Operating System :: OS Independent
